djangocms_googlemap/__init__.py
djangocms_googlemap/cms_plugins.py
djangocms_googlemap/models.py
djangocms_googlemap/locale/af/LC_MESSAGES/django.mo
djangocms_googlemap/locale/af/LC_MESSAGES/django.po
djangocms_googlemap/locale/ar/LC_MESSAGES/django.mo
djangocms_googlemap/locale/ar/LC_MESSAGES/django.po
djangocms_googlemap/locale/be/LC_MESSAGES/django.mo
djangocms_googlemap/locale/be/LC_MESSAGES/django.po
djangocms_googlemap/locale/bg/LC_MESSAGES/django.mo
djangocms_googlemap/locale/bg/LC_MESSAGES/django.po
djangocms_googlemap/locale/bn/LC_MESSAGES/django.mo
djangocms_googlemap/locale/bn/LC_MESSAGES/django.po
djangocms_googlemap/locale/ca/LC_MESSAGES/django.mo
djangocms_googlemap/locale/ca/LC_MESSAGES/django.po
djangocms_googlemap/locale/cmn/LC_MESSAGES/django.mo
djangocms_googlemap/locale/cmn/LC_MESSAGES/django.po
djangocms_googlemap/locale/cs/LC_MESSAGES/django.mo
djangocms_googlemap/locale/cs/LC_MESSAGES/django.po
djangocms_googlemap/locale/cy/LC_MESSAGES/django.mo
djangocms_googlemap/locale/cy/LC_MESSAGES/django.po
djangocms_googlemap/locale/da/LC_MESSAGES/django.mo
djangocms_googlemap/locale/da/LC_MESSAGES/django.po
djangocms_googlemap/locale/de/LC_MESSAGES/django.mo
djangocms_googlemap/locale/de/LC_MESSAGES/django.po
djangocms_googlemap/locale/el/LC_MESSAGES/django.mo
djangocms_googlemap/locale/el/LC_MESSAGES/django.po
djangocms_googlemap/locale/en/LC_MESSAGES/django.mo
djangocms_googlemap/locale/en/LC_MESSAGES/django.po
djangocms_googlemap/locale/es/LC_MESSAGES/django.mo
djangocms_googlemap/locale/es/LC_MESSAGES/django.po
djangocms_googlemap/locale/es_AR/LC_MESSAGES/django.mo
djangocms_googlemap/locale/es_AR/LC_MESSAGES/django.po
djangocms_googlemap/locale/es_BO/LC_MESSAGES/django.mo
djangocms_googlemap/locale/es_BO/LC_MESSAGES/django.po
djangocms_googlemap/locale/es_DO/LC_MESSAGES/django.mo
djangocms_googlemap/locale/es_DO/LC_MESSAGES/django.po
djangocms_googlemap/locale/et/LC_MESSAGES/django.mo
djangocms_googlemap/locale/et/LC_MESSAGES/django.po
djangocms_googlemap-2.2.0.dist-info/LICENSE
djangocms_googlemap-2.2.0.dist-info/METADATA
djangocms_googlemap-2.2.0.dist-info/WHEEL
djangocms_googlemap-2.2.0.dist-info/top_level.txt
djangocms_googlemap-2.2.0.dist-info/RECORD
